structuregen/__init__.py
structuregen/cli.py
structuregen-0.1.0.dist-info/licenses/LICENSE
structuregen-0.1.0.dist-info/METADATA
structuregen-0.1.0.dist-info/WHEEL
structuregen-0.1.0.dist-info/entry_points.txt
structuregen-0.1.0.dist-info/top_level.txt
structuregen-0.1.0.dist-info/RECORD
