Metadata-Version: 2.4
Name: structuregen
Version: 0.1.0
Summary: Generate a FastAPI-style backend folder structure with one command
Author-email: Sushurht Samson <samsushruth@gmail.com>
License: MIT
Requires-Python: >=3.7
License-File: LICENSE
Dynamic: license-file
